{
  "resourceType": "ValueSet",
  "id": "quantityUnits",
  "meta": {
    "profile": [
      "http://hl7.org/fhir/StructureDefinition/shareablevalueset"
    ]
  },
  "text": {
    "status": "generated",
    "div": "<div xmlns=\"http://www.w3.org/1999/xhtml\"><h2>IPSQuantityUnits</h2><div><p>Quantity Units</p>\n</div><p>This value set includes codes from the following code systems:</p><ul><li>Include all codes defined in <a href=\"http://unitsofmeasure.org\"><code>http://unitsofmeasure.org</code></a></li></ul></div>"
  },
  "url": "http://hl7.org/fhir/ips/ValueSet/quantityUnits",
  "identifier": [
    {
      "use": "official",
      "system": "http://art-decor.org/ns/oids/vs",
      "value": "2.16.840.1.113883.11.22.28"
    }
  ],
  "version": "1",
  "name": "IPSQuantityUnits",
  "title": "Quantity Units",
  "status": "draft",
  "experimental": false,
  "date": "2018-03-30T11:34:46-05:00",
  "publisher": "HL7 International",
  "contact": [
    {
      "name": "HL7 International",
      "telecom": [
        {
          "system": "phone",
          "value": "+1 734 677 7777 "
        },
        {
          "system": "fax",
          "value": "+1 734 677 6622"
        },
        {
          "system": "email",
          "value": "info@hl7.org"
        }
      ]
    }
  ],
  "description": "Quantity Units",
  "jurisdiction": [
    {
      "coding": [
        {
          "system": "http://unstats.un.org/unsd/methods/m49/m49.htm",
          "code": "001",
          "display": "World"
        }
      ]
    }
  ],
  "immutable": false,
  "compose": {
    "include": [
      {
        "system": "http://unitsofmeasure.org"
      }
    ]
  }
}