<?xml version="1.0" encoding="utf-8"?>
<StructureDefinition xmlns="http://hl7.org/fhir">
	<id value="Procedure-uv-ips"/>
	<meta>
		<lastUpdated value="2018-02-20T12:54:56.053+01:00"/>
	</meta>
	<url value="http://hl7.org/fhir/uv/ips/StructureDefinition/Procedure-uv-ips"/>
	<name value="Procedure_uv_ips"/>
	<title value="Procedure (IPS)"/>
	<status value="draft"/>
	<date value="2017-10-27T13:43:30.381+02:00"/>
	<description value="This profile represents the constraints applied to the Procedure resource by the IPS project, which specifies an entry of the History of Procedure for the international patient summary based on the FHIR standard R4. "/>
	<kind value="resource"/>
	<abstract value="false"/>
	<type value="Procedure"/>
	<baseDefinition value="http://hl7.org/fhir/StructureDefinition/Procedure"/>
	<derivation value="constraint"/>
	<differential>
		<element id="Procedure">
			<path value="Procedure"/>
		</element>
		<element id="Procedure.extension:statementDetail">
			<path value="Procedure.extension"/>
			<sliceName value="statementDetail"/>
			<type>
				<code value="Extension"/>
				<profile value="http://hl7.org/fhir/uv/ips/StructureDefinition/statement-uv-ips"/>
			</type>
			<mustSupport value="true"/>
		</element>
		<element id="Procedure.status">
			<path value="Procedure.status"/>
			<mustSupport value="true"/>
		</element>
		<element id="Procedure.code">
			<path value="Procedure.code"/>
			<mustSupport value="true"/>
			<binding>
				<extension url="http://hl7.org/fhir/StructureDefinition/elementdefinition-bindingName">
					<valueString value="ProcedureCode"/>
				</extension>
				<strength value="preferred"/>
				<valueSet value="http://hl7.org/fhir/uv/ips/ValueSet/procedures-uv-ips"/>
			</binding>
		</element>
		<element id="Procedure.code.coding">
			<path value="Procedure.code.coding"/>
			<slicing>
				<description value="Discriminated by value set biding"/>
				<rules value="open"/>
			</slicing>
			<mustSupport value="true"/>
		</element>
		<element id="Procedure.code.coding:absentOrUnknownProcedure">
			<path value="Procedure.code.coding"/>
			<sliceName value="absentOrUnknownProcedure"/>
			<type>
				<code value="Coding"/>
				<profile value="http://hl7.org/fhir/uv/ips/StructureDefinition/Coding-uv-ips"/>
			</type>
			<mustSupport value="true"/>
			<binding>
				<extension url="http://hl7.org/fhir/StructureDefinition/elementdefinition-bindingName">
					<valueString value="absentOrUnknownProcedure"/>
				</extension>
				<strength value="required"/>
				<description value="A code to identify absent or unknown procedures"/>
				<valueSet value="http://hl7.org/fhir/uv/ips/ValueSet/absent-or-unknown-procedures-uv-ips"/>
			</binding>
		</element>
		<element id="Procedure.code.coding:procedureCode">
			<path value="Procedure.code.coding"/>
			<sliceName value="procedureCode"/>
			<type>
				<code value="Coding"/>
				<profile value="http://hl7.org/fhir/uv/ips/StructureDefinition/Coding-uv-ips"/>
			</type>
			<mustSupport value="true"/>
			<binding>
				<extension url="http://hl7.org/fhir/StructureDefinition/elementdefinition-bindingName">
					<valueString value="ProcedureCode"/>
				</extension>
				<strength value="preferred"/>
				<valueSet value="http://hl7.org/fhir/uv/ips/ValueSet/procedures-uv-ips"/>
			</binding>
		</element>
		<element id="Procedure.subject">
			<path value="Procedure.subject"/>
			<definition value="The person on which the procedure was performed."/>
			<type>
				<code value="Reference"/>
				<targetProfile value="http://hl7.org/fhir/uv/ips/StructureDefinition/Patient-uv-ips"/>
			</type>
			<mustSupport value="true"/>
		</element>
		<element id="Procedure.subject.reference">
			<path value="Procedure.subject.reference"/>
			<min value="1"/>
			<mustSupport value="true"/>
		</element>
		<element id="Procedure.performed[x]">
			<path value="Procedure.performed[x]"/>
			<slicing>
				<discriminator>
					<type value="type"/>
					<path value="$this"/>
				</discriminator>
				<rules value="open"/>
			</slicing>
			<min value="1"/>
			<max value="1"/>
			<mustSupport value="true"/>
		</element>
		<element id="Procedure.performedDateTime">
			<path value="Procedure.performedDateTime"/>
			<sliceName value="performedDateTime"/>
			<type>
				<code value="dateTime"/>
			</type>
		</element>
		<element id="Procedure.performedDateTime:data-absent-reason">
			<path value="Procedure.performedDateTime.extension"/>
			<sliceName value="data-absent-reason"/>
			<short value="performed[x] absence reason"/>
			<definition value="Provides a reason why the performed is missing."/>
			<max value="1"/>
			<type>
				<code value="Extension"/>
				<profile value="http://hl7.org/fhir/StructureDefinition/data-absent-reason"/>
			</type>
			<mustSupport value="true"/>
		</element>
		<element id="Procedure.performedPeriod">
			<path value="Procedure.performedPeriod"/>
			<sliceName value="performedPeriod"/>
			<type>
				<code value="Period"/>
			</type>
		</element>
		<element id="Procedure.performedPeriod:data-absent-reason">
			<path value="Procedure.performedPeriod.extension"/>
			<sliceName value="data-absent-reason"/>
			<short value="performed[x] absence reason"/>
			<definition value="Provides a reason why the performed is missing."/>
			<max value="1"/>
			<type>
				<code value="Extension"/>
				<profile value="http://hl7.org/fhir/StructureDefinition/data-absent-reason"/>
			</type>
			<mustSupport value="true"/>
		</element>
		<element id="Procedure.performedString">
			<path value="Procedure.performedString"/>
			<sliceName value="performedString"/>
			<type>
				<code value="string"/>
			</type>
		</element>
		<element id="Procedure.performedString:data-absent-reason">
			<path value="Procedure.performedString.extension"/>
			<sliceName value="data-absent-reason"/>
			<short value="performed[x] absence reason"/>
			<definition value="Provides a reason why the performed is missing."/>
			<max value="1"/>
			<type>
				<code value="Extension"/>
				<profile value="http://hl7.org/fhir/StructureDefinition/data-absent-reason"/>
			</type>
			<mustSupport value="true"/>
		</element>
		<element id="Procedure.performedAge">
			<path value="Procedure.performedAge"/>
			<sliceName value="performedAge"/>
			<type>
				<code value="Age"/>
			</type>
		</element>
		<element id="Procedure.performedAge:data-absent-reason">
			<path value="Procedure.performedAge.extension"/>
			<sliceName value="data-absent-reason"/>
			<short value="performed[x] absence reason"/>
			<definition value="Provides a reason why the performed is missing."/>
			<max value="1"/>
			<type>
				<code value="Extension"/>
				<profile value="http://hl7.org/fhir/StructureDefinition/data-absent-reason"/>
			</type>
			<mustSupport value="true"/>
		</element>
		<element id="Procedure.performedRange">
			<path value="Procedure.performedRange"/>
			<sliceName value="performedRange"/>
			<type>
				<code value="Range"/>
			</type>
		</element>
		<element id="Procedure.performedRange:data-absent-reason">
			<path value="Procedure.performedRange.extension"/>
			<sliceName value="data-absent-reason"/>
			<short value="performed[x] absence reason"/>
			<definition value="Provides a reason why the performed is missing."/>
			<max value="1"/>
			<type>
				<code value="Extension"/>
				<profile value="http://hl7.org/fhir/StructureDefinition/data-absent-reason"/>
			</type>
			<mustSupport value="true"/>
		</element>
		<element id="Procedure.performer">
			<path value="Procedure.performer"/>
			<mustSupport value="true"/>
		</element>
		<element id="Procedure.performer.actor">
			<path value="Procedure.performer.actor"/>
			<type>
				<code value="Reference"/>
				<targetProfile value="http://hl7.org/fhir/StructureDefinition/Patient"/>
				<targetProfile value="http://hl7.org/fhir/StructureDefinition/RelatedPerson"/>
				<targetProfile value="http://hl7.org/fhir/uv/ips/StructureDefinition/Device-observer-uv-ips"/>
				<targetProfile value="http://hl7.org/fhir/uv/ips/StructureDefinition/Practitioner-uv-ips"/>
				<targetProfile value="http://hl7.org/fhir/uv/ips/StructureDefinition/Organization-observation-uv-ips"/>
			</type>
			<mustSupport value="true"/>
		</element>
		<element id="Procedure.performer.onBehalfOf">
			<path value="Procedure.performer.onBehalfOf"/>
			<type>
				<code value="Reference"/>
				<targetProfile value="http://hl7.org/fhir/uv/ips/StructureDefinition/Organization-observation-uv-ips"/>
			</type>
			<mustSupport value="true"/>
		</element>
		<element id="Procedure.bodySite">
			<path value="Procedure.bodySite"/>
			<type>
				<code value="CodeableConcept"/>
				<profile value="http://hl7.org/fhir/uv/ips/StructureDefinition/CodeableConcept-uv-ips"/>
			</type>
			<mustSupport value="true"/>
			<binding>
				<extension url="http://hl7.org/fhir/StructureDefinition/elementdefinition-bindingName">
					<valueString value="BodySite"/>
				</extension>
				<strength value="example"/>
				<valueSet value="http://hl7.org/fhir/ValueSet/body-site"/>
			</binding>
		</element>
	</differential>
</StructureDefinition>
